{
    "keep": {
        "days": true,
        "amount": 7
    },
    "auditLog": "D:\\Web Development\\Next Level\\Bookshelf\\server\\logs\\winston\\successes\\.e944c95fda75674c379237710229f347488b6f57-audit.json",
    "files": [
        {
            "date": 1689311171017,
            "name": "D:\\Web Development\\Next Level\\Bookshelf\\server\\logs\\winston\\successes\\success-2023-07-14-11.log",
            "hash": "230021848ca81f2bb96b2a06baf0b4b5e939e2beb7358d4d319654eb2d1424b9"
        },
        {
            "date": 1689314814702,
            "name": "D:\\Web Development\\Next Level\\Bookshelf\\server\\logs\\winston\\successes\\success-2023-07-14-12.log",
            "hash": "8bd0537f101194d4c4248f4d7fe65d3921f4d4c9608763cefc4d9dcc56891fa1"
        },
        {
            "date": 1689318019366,
            "name": "D:\\Web Development\\Next Level\\Bookshelf\\server\\logs\\winston\\successes\\success-2023-07-14-13.log",
            "hash": "a6b5c6247f9ee962327a43b2db348c2ab150897897636dcca59f0313c340bc33"
        }
    ],
    "hashType": "sha256"
}